django_trumbo/__init__.py
django_trumbo/apps.py
django_trumbo/widgets.py
django_trumbo/__pycache__/__init__.cpython-37.pyc
django_trumbo/__pycache__/widgets.cpython-37.pyc
django_trumbo/static/trumbowyg/jquery.min.js
django_trumbo/static/trumbowyg/trumbowyg.js
django_trumbo/static/trumbowyg/trumbowyg.min.js
django_trumbo/static/trumbowyg/langs/ar.js
django_trumbo/static/trumbowyg/langs/ar.min.js
django_trumbo/static/trumbowyg/langs/bg.js
django_trumbo/static/trumbowyg/langs/bg.min.js
django_trumbo/static/trumbowyg/langs/by.js
django_trumbo/static/trumbowyg/langs/by.min.js
django_trumbo/static/trumbowyg/langs/ca.js
django_trumbo/static/trumbowyg/langs/ca.min.js
django_trumbo/static/trumbowyg/langs/cs.js
django_trumbo/static/trumbowyg/langs/cs.min.js
django_trumbo/static/trumbowyg/langs/da.js
django_trumbo/static/trumbowyg/langs/da.min.js
django_trumbo/static/trumbowyg/langs/de.js
django_trumbo/static/trumbowyg/langs/de.min.js
django_trumbo/static/trumbowyg/langs/el.js
django_trumbo/static/trumbowyg/langs/el.min.js
django_trumbo/static/trumbowyg/langs/es.js
django_trumbo/static/trumbowyg/langs/es.min.js
django_trumbo/static/trumbowyg/langs/es_ar.js
django_trumbo/static/trumbowyg/langs/es_ar.min.js
django_trumbo/static/trumbowyg/langs/fa.js
django_trumbo/static/trumbowyg/langs/fa.min.js
django_trumbo/static/trumbowyg/langs/fi.js
django_trumbo/static/trumbowyg/langs/fi.min.js
django_trumbo/static/trumbowyg/langs/fr.js
django_trumbo/static/trumbowyg/langs/fr.min.js
django_trumbo/static/trumbowyg/langs/he.js
django_trumbo/static/trumbowyg/langs/he.min.js
django_trumbo/static/trumbowyg/langs/hr.js
django_trumbo/static/trumbowyg/langs/hr.min.js
django_trumbo/static/trumbowyg/langs/hu.js
django_trumbo/static/trumbowyg/langs/hu.min.js
django_trumbo/static/trumbowyg/langs/id.js
django_trumbo/static/trumbowyg/langs/id.min.js
django_trumbo/static/trumbowyg/langs/it.js
django_trumbo/static/trumbowyg/langs/it.min.js
django_trumbo/static/trumbowyg/langs/ja.js
django_trumbo-0.0.1.dist-info/LICENSE
django_trumbo-0.0.1.dist-info/METADATA
django_trumbo-0.0.1.dist-info/WHEEL
django_trumbo-0.0.1.dist-info/top_level.txt
django_trumbo-0.0.1.dist-info/RECORD
